rampy/__init__.py
rampy/baseline.py
rampy/dac.py
rampy/filters.py
rampy/functions.py
rampy/maps.py
rampy/mixing.py
rampy/ml_classification.py
rampy/ml_exploration.py
rampy/ml_regressor.py
rampy/peak_area.py
rampy/peak_shapes.py
rampy/plotting.py
rampy/rameau.py
rampy/spectranization.py
rampy/tlcorrection.py
rampy/notused/IRTABS.py
rampy-0.6.2.dist-info/licenses/LICENSE
rampy-0.6.2.dist-info/METADATA
rampy-0.6.2.dist-info/WHEEL
rampy-0.6.2.dist-info/top_level.txt
rampy-0.6.2.dist-info/RECORD
