Metadata-Version: 2.4
Name: rampy
Version: 0.6.2
Summary: A Python module containing functions to treat spectroscopic (XANES, Raman, IR...) data
Author-email: Charles Le Losq <lelosq@ipgp.fr>
License: GNU GENERAL PUBLIC LICENSE
Project-URL: Homepage, https://github.com/charlesll/rampy/
Project-URL: Documentation, http://charlesll.github.io/rampy/html/index.html
Project-URL: Repository, https://github.com/charlesll/rampy.git
Project-URL: Bug Tracker, https://github.com/charlesll/rampy/issues
Project-URL: Changelog, https://github.com/charlesll/rampy/NEWS.md
Keywords: spectroscopy,data,treatment,Raman,XANES,Infrared,NMR
Classifier: Development Status :: 5 - Production/Stable
Classifier: Programming Language :: Python
Requires-Python: >=3.10
License-File: LICENSE
Requires-Dist: numpy>=1.12
Requires-Dist: scipy>=1.10.0
Requires-Dist: scikit-learn>=1.0.0
Requires-Dist: pandas
Requires-Dist: xlrd
Requires-Dist: matplotlib
Requires-Dist: cvxpy>=1.1
Requires-Dist: plotly
Provides-Extra: gcvspline
Requires-Dist: gcvspline; extra == "gcvspline"
Dynamic: license-file
